brLibrarydocumentor/__init__.py
brLibrarydocumentor/docBuilder.py
brLibrarydocumentor/functionblock.py
brLibrarydocumentor/plugin.py
brLibrarydocumentor/Templates/Markdown/DataTypes.md
brLibrarydocumentor/Templates/Markdown/FunctionBlockTemplate.md
brLibrarydocumentor/Templates/Markdown/FunctionBlocksAndFunctions.md
brLibrarydocumentor/Templates/Markdown/GeneralInformation.md
brLibrarydocumentor/Templates/html/fbDescription.html
brLibrarydocumentor/Templates/html/fbFaceplate.html
brLibrarydocumentor/Templates/html/fbParameterTable.html
brLibrarydocumentor/Templates/html/fbTitle.html
brLibrarydocumentor/Templates/html/functionBlockPage.html
brLibrarydocumentor/Templates/html/libDatatypePage.html
brLibrarydocumentor/Templates/html/libDatatypeTable.html
brLibrarydocumentor/Templates/html/libEnumPage.html
brLibrarydocumentor/Templates/html/libEnumTable.html
brLibrarydocumentor/css/fubFacePlateStyles.css
BRLibraryDocumentor-1.0.0.dist-info/LICENSE
BRLibraryDocumentor-1.0.0.dist-info/METADATA
BRLibraryDocumentor-1.0.0.dist-info/WHEEL
BRLibraryDocumentor-1.0.0.dist-info/entry_points.txt
BRLibraryDocumentor-1.0.0.dist-info/top_level.txt
BRLibraryDocumentor-1.0.0.dist-info/RECORD
